<?xml version="1.0" encoding="utf-8" ?>
<c2layout>
    <name>TabuleiroPORRA</name>
    <sid>599294292725211</sid>
    <event-sheet>Event sheet 1</event-sheet>
    <size>
        <width>720</width>
        <height>1280</height>
    </size>
    <margins>
        <horizontal>500</horizontal>
        <vertical>500</vertical>
    </margins>
    <unbounded-scrolling>0</unbounded-scrolling>
    <layers>
        <layer name="TELAPRETA" sid="997841902301710">
            <initially-visible>1</initially-visible>
            <background-color>255,255,255</background-color>
            <transparent>0</transparent>
            <parallax>
                <x>1</x>
                <y>1</y>
            </parallax>
            <zoom-rate>1</zoom-rate>
            <opacity>1</opacity>
            <force-own-texture>0</force-own-texture>
            <global>0</global>
            <use-render-cells>0</use-render-cells>
            <blend-mode>0</blend-mode>
            <effect-fallback>0</effect-fallback>
            <instances>
                <instance type="PretoFundo" uid="6">
                    <properties>
                        <initial-visibility>Visible</initial-visibility>
                        <initial-animation>Default</initial-animation>
                        <initial-frame>0</initial-frame>
                        <collisions>Enabled</collisions>
                    </properties>
                    <blend-mode>0</blend-mode>
                    <effect-fallback>0</effect-fallback>
                    <world>
                        <x>359</x>
                        <y>639</y>
                        <z>0</z>
                        <width>730</width>
                        <height>1289</height>
                        <depth>0</depth>
                        <hotspotX>0.5</hotspotX>
                        <hotspotY>0.5</hotspotY>
                        <angle>0</angle>
                        <opacity>1</opacity>
                    </world>
                </instance>
                <instance type="DeusTalles" uid="9">
                    <properties>
                        <initial-visibility>Visible</initial-visibility>
                        <hotspot>Top-left</hotspot>
                    </properties>
                    <behavior-instances>
                        <behavior-instance type="LiteTween">
                            <properties>
                                <active-on-start>Yes</active-on-start>
                                <tweened-property>Position</tweened-property>
                                <function>EaseOutBounce</function>
                                <target>-325, -3</target>
                                <target-mode>Absolute</target-mode>
                                <duration>3</duration>
                                <enforce-mode>Enforce</enforce-mode>
                            </properties>
                        </behavior-instance>
                    </behavior-instances>
                    <blend-mode>0</blend-mode>
                    <effect-fallback>0</effect-fallback>
                    <world>
                        <x>-325</x>
                        <y>-1000</y>
                        <z>0</z>
                        <width>1111</width>
                        <height>1419</height>
                        <depth>0</depth>
                        <hotspotX>0</hotspotX>
                        <hotspotY>0</hotspotY>
                        <angle>0</angle>
                        <opacity>1</opacity>
                    </world>
                </instance>
                <instance type="AnjoTalles1" uid="17">
                    <properties>
                        <initial-visibility>Visible</initial-visibility>
                        <hotspot>Top-left</hotspot>
                    </properties>
                    <behavior-instances>
                        <behavior-instance type="LiteTween">
                            <properties>
                                <active-on-start>Yes</active-on-start>
                                <tweened-property>Position</tweened-property>
                                <function>EaseInOutBack</function>
                                <target>614, 606</target>
                                <target-mode>Absolute</target-mode>
                                <duration>4</duration>
                                <enforce-mode>Enforce</enforce-mode>
                            </properties>
                        </behavior-instance>
                    </behavior-instances>
                    <blend-mode>0</blend-mode>
                    <effect-fallback>0</effect-fallback>
                    <world>
                        <x>1159</x>
                        <y>902</y>
                        <z>0</z>
                        <width>199</width>
                        <height>135</height>
                        <depth>0</depth>
                        <hotspotX>0</hotspotX>
                        <hotspotY>0</hotspotY>
                        <angle>0</angle>
                        <opacity>1</opacity>
                    </world>
                </instance>
                <instance type="Belquior" uid="18">
                    <properties>
                        <initial-visibility>Visible</initial-visibility>
                        <hotspot>Top-left</hotspot>
                    </properties>
                    <behavior-instances>
                        <behavior-instance type="LiteTween">
                            <properties>
                                <active-on-start>Yes</active-on-start>
                                <tweened-property>Position</tweened-property>
                                <function>EaseOutBounce</function>
                                <target>-78, 867</target>
                                <target-mode>Absolute</target-mode>
                                <duration>7</duration>
                                <enforce-mode>Enforce</enforce-mode>
                            </properties>
                        </behavior-instance>
                    </behavior-instances>
                    <blend-mode>0</blend-mode>
                    <effect-fallback>0</effect-fallback>
                    <world>
                        <x>-78</x>
                        <y>1200</y>
                        <z>0</z>
                        <width>503</width>
                        <height>459</height>
                        <depth>0</depth>
                        <hotspotX>0</hotspotX>
                        <hotspotY>0</hotspotY>
                        <angle>0</angle>
                        <opacity>1</opacity>
                    </world>
                </instance>
                <instance type="AnjoTalles2" uid="19">
                    <properties>
                        <initial-visibility>Visible</initial-visibility>
                        <hotspot>Top-left</hotspot>
                    </properties>
                    <behavior-instances>
                        <behavior-instance type="LiteTween">
                            <properties>
                                <active-on-start>Yes</active-on-start>
                                <tweened-property>Position</tweened-property>
                                <function>EaseInOutBack</function>
                                <target>602, 370</target>
                                <target-mode>Absolute</target-mode>
                                <duration>4</duration>
                                <enforce-mode>Enforce</enforce-mode>
                            </properties>
                        </behavior-instance>
                    </behavior-instances>
                    <blend-mode>0</blend-mode>
                    <effect-fallback>0</effect-fallback>
                    <world>
                        <x>1131</x>
                        <y>356</y>
                        <z>0</z>
                        <width>185</width>
                        <height>126</height>
                        <depth>0</depth>
                        <hotspotX>0</hotspotX>
                        <hotspotY>0</hotspotY>
                        <angle>0</angle>
                        <opacity>1</opacity>
                    </world>
                </instance>
                <instance type="AnjoTalles3" uid="10">
                    <properties>
                        <initial-visibility>Visible</initial-visibility>
                        <hotspot>Top-left</hotspot>
                    </properties>
                    <behavior-instances>
                        <behavior-instance type="LiteTween">
                            <properties>
                                <active-on-start>Yes</active-on-start>
                                <tweened-property>Position</tweened-property>
                                <function>EaseInOutBack</function>
                                <target>546, 159</target>
                                <target-mode>Absolute</target-mode>
                                <duration>4</duration>
                                <enforce-mode>Enforce</enforce-mode>
                            </properties>
                        </behavior-instance>
                    </behavior-instances>
                    <blend-mode>0</blend-mode>
                    <effect-fallback>0</effect-fallback>
                    <world>
                        <x>1166</x>
                        <y>69</y>
                        <z>0</z>
                        <width>197</width>
                        <height>135</height>
                        <depth>0</depth>
                        <hotspotX>0</hotspotX>
                        <hotspotY>0</hotspotY>
                        <angle>0</angle>
                        <opacity>1</opacity>
                    </world>
                </instance>
                <instance type="AnjoTalles4" uid="12">
                    <properties>
                        <initial-visibility>Visible</initial-visibility>
                        <hotspot>Top-left</hotspot>
                    </properties>
                    <behavior-instances>
                        <behavior-instance type="LiteTween">
                            <properties>
                                <active-on-start>Yes</active-on-start>
                                <tweened-property>Position</tweened-property>
                                <function>EaseInOutBack</function>
                                <target>504, 0</target>
                                <target-mode>Absolute</target-mode>
                                <duration>4</duration>
                                <enforce-mode>Enforce</enforce-mode>
                            </properties>
                        </behavior-instance>
                    </behavior-instances>
                    <blend-mode>0</blend-mode>
                    <effect-fallback>0</effect-fallback>
                    <world>
                        <x>637</x>
                        <y>-278</y>
                        <z>0</z>
                        <width>199</width>
                        <height>137</height>
                        <depth>0</depth>
                        <hotspotX>0</hotspotX>
                        <hotspotY>0</hotspotY>
                        <angle>0</angle>
                        <opacity>1</opacity>
                    </world>
                </instance>
                <instance type="AnjoTalles5" uid="16">
                    <properties>
                        <initial-visibility>Visible</initial-visibility>
                        <hotspot>Top-left</hotspot>
                    </properties>
                    <behavior-instances>
                        <behavior-instance type="LiteTween">
                            <properties>
                                <active-on-start>Yes</active-on-start>
                                <tweened-property>Position</tweened-property>
                                <function>EaseInOutBack</function>
                                <target>-47, 643</target>
                                <target-mode>Absolute</target-mode>
                                <duration>4</duration>
                                <enforce-mode>Enforce</enforce-mode>
                            </properties>
                        </behavior-instance>
                    </behavior-instances>
                    <blend-mode>0</blend-mode>
                    <effect-fallback>0</effect-fallback>
                    <world>
                        <x>-343</x>
                        <y>762</y>
                        <z>0</z>
                        <width>216</width>
                        <height>147</height>
                        <depth>0</depth>
                        <hotspotX>0</hotspotX>
                        <hotspotY>0</hotspotY>
                        <angle>0</angle>
                        <opacity>1</opacity>
                    </world>
                </instance>
                <instance type="AnjoTalles6" uid="13">
                    <properties>
                        <initial-visibility>Visible</initial-visibility>
                        <hotspot>Top-left</hotspot>
                    </properties>
                    <behavior-instances>
                        <behavior-instance type="LiteTween">
                            <properties>
                                <active-on-start>Yes</active-on-start>
                                <tweened-property>Position</tweened-property>
                                <function>EaseInOutBack</function>
                                <target>-67, 410</target>
                                <target-mode>Absolute</target-mode>
                                <duration>4</duration>
                                <enforce-mode>Enforce</enforce-mode>
                            </properties>
                        </behavior-instance>
                    </behavior-instances>
                    <blend-mode>0</blend-mode>
                    <effect-fallback>0</effect-fallback>
                    <world>
                        <x>-432</x>
                        <y>359</y>
                        <z>0</z>
                        <width>199</width>
                        <height>151</height>
                        <depth>0</depth>
                        <hotspotX>0</hotspotX>
                        <hotspotY>0</hotspotY>
                        <angle>0</angle>
                        <opacity>1</opacity>
                    </world>
                </instance>
                <instance type="AnjoTalles7" uid="14">
                    <properties>
                        <initial-visibility>Visible</initial-visibility>
                        <hotspot>Top-left</hotspot>
                    </properties>
                    <behavior-instances>
                        <behavior-instance type="LiteTween">
                            <properties>
                                <active-on-start>Yes</active-on-start>
                                <tweened-property>Position</tweened-property>
                                <function>EaseInOutBack</function>
                                <target>24, 10</target>
                                <target-mode>Absolute</target-mode>
                                <duration>4</duration>
                                <enforce-mode>Enforce</enforce-mode>
                            </properties>
                        </behavior-instance>
                    </behavior-instances>
                    <blend-mode>0</blend-mode>
                    <effect-fallback>0</effect-fallback>
                    <world>
                        <x>-1</x>
                        <y>-238</y>
                        <z>0</z>
                        <width>209</width>
                        <height>135</height>
                        <depth>0</depth>
                        <hotspotX>0</hotspotX>
                        <hotspotY>0</hotspotY>
                        <angle>0</angle>
                        <opacity>1</opacity>
                    </world>
                </instance>
            </instances>
            <effects />
        </layer>
    </layers>
    <nonworld-instances />
    <effects />
</c2layout>
