<?xml version="1.0" encoding="utf-8" ?>
<c2eventsheet>
    <!--All the 'name' attributes are ignored by Construct 2 - they are there for readability only.-->
    <name>Tabuleiro8</name>
    <events>
        <include>TabuleiroTodos</include>
        <event-block sid="321228286247820">
            <conditions>
                <condition id="6" name="On object clicked" sid="222586274460958" type="Mouse">
                    <param id="0" name="Mouse button">0</param>
                    <param id="1" name="Click type">0</param>
                    <param id="2" name="Object clicked">AVANÇAR</param>
                </condition>
            </conditions>
            <actions>
                <action behavior="LiteTween" id="10" name="Start" sid="951144491693252" type="Larissa_Player">
                    <param id="0" name="Start Mode">0</param>
                    <param id="1" name="Force use current">1</param>
                </action>
            </actions>
        </event-block>
    </events>
</c2eventsheet>
